AdE/0_verilog/2_exr/0_testbench/0_clock.v
module clock(output out);

    reg clock;
    initial
        begin
            clock = 0;
        end
    
    assign out = clock;

    always
        begin
            #1 clock = ~clock;
        end

endmodule

AdE/0_verilog/2_exr/0_testbench/1_test.v

/*IL MODULO DI TEST E' UN MODULO SENZA PARAMETRI*/

    /*DICHIARAZIONI WIRE PER OGNI OUTPUT*/
 
    /*DICHIARAZIONI REG PER OGNI INPUT*/
    //NESSUN INPUT PER IL CLOCK

    /*ISTANZIAZIONE DEL COMPONENTE*/



    /*PROGRAMMA DI PROVA: ASSEGNA VALORI DIVERSI AGLI INPUT*/
    /*VALORI DIVERSI IN TEMPI DIVERSI*/

/*FINE SCHEMA*/

module test();

wire out;

clock t_clock(out);

initial
    begin
        $monitor("%t %d", $time, out);
        //PARTE DA AGGIUNGERE PER TESTARE CON GTKWAVE
        $dumpfile("clock.vcd");
        $dumpvars;
        //

        #30
        $finish;
    end

endmodule

AdE/0_verilog/2_exr/0_testbench/clock.vcd
$date
	Fri Jan  8 18:51:35 2021
$end
$version
	Icarus Verilog
$end
$timescale
	1s
$end
$scope module test $end
$var wire 1 ! out $end
$scope module t_clock $end
$var wire 1 ! out $end
$var reg 1 " clock $end
$upscope $end
$upscope $end
$enddefinitions $end
#0
$dumpvars
0"
0!
$end
#1
1!
1"
#2
0!
0"
#3
1!
1"
#4
0!
0"
#5
1!
1"
#6
0!
0"
#7
1!
1"
#8
0!
0"
#9
1!
1"
#10
0!
0"
#11
1!
1"
#12
0!
0"
#13
1!
1"
#14
0!
0"
#15
1!
1"
#16
0!
0"
#17
1!
1"
#18
0!
0"
#19
1!
1"
#20
0!
0"
#21
1!
1"
#22
0!
0"
#23
1!
1"
#24
0!
0"
#25
1!
1"
#26
0!
0"
#27
1!
1"
#28
0!
0"
#29
1!
1"
#30
0!
0"
